cdk_bootstrapless_synthesizer/__init__.py
cdk_bootstrapless_synthesizer/py.typed
cdk_bootstrapless_synthesizer/_jsii/__init__.py
cdk_bootstrapless_synthesizer/_jsii/cdk-bootstrapless-synthesizer@2.3.2.jsii.tgz
cdk_bootstrapless_synthesizer-2.3.2.dist-info/LICENSE
cdk_bootstrapless_synthesizer-2.3.2.dist-info/METADATA
cdk_bootstrapless_synthesizer-2.3.2.dist-info/NOTICE
cdk_bootstrapless_synthesizer-2.3.2.dist-info/WHEEL
cdk_bootstrapless_synthesizer-2.3.2.dist-info/top_level.txt
cdk_bootstrapless_synthesizer-2.3.2.dist-info/RECORD
