Metadata-Version: 2.1
Name: cdk-bootstrapless-synthesizer
Version: 2.3.2
Summary: Generate directly usable AWS CloudFormation template with aws-cdk v2.
Home-page: https://github.com/aws-samples/cdk-bootstrapless-synthesizer.git
Author: wchaws
License: Apache-2.0
Project-URL: Source, https://github.com/aws-samples/cdk-bootstrapless-synthesizer.git
Platform: UNKNOWN
Classifier: Intended Audience :: Developers
Classifier: Operating System :: OS Independent
Classifier: Programming Language :: JavaScript
Classifier: Programming Language :: Python :: 3 :: Only
Classifier: Programming Language :: Python :: 3.7
Classifier: Programming Language :: Python :: 3.8
Classifier: Programming Language :: Python :: 3.9
Classifier: Programming Language :: Python :: 3.10
Classifier: Typing :: Typed
Classifier: Development Status :: 5 - Production/Stable
Classifier: License :: OSI Approved
Requires-Python: ~=3.7
License-File: LICENSE
License-File: NOTICE
Requires-Dist: aws-cdk-lib (<3.0.0,>=2.0.0)
Requires-Dist: aws-cdk.aws-batch-alpha (<3.0.0,>=2.8.0.a0)
Requires-Dist: constructs (<11.0.0,>=10.0.5)
Requires-Dist: jsii (<2.0.0,>=1.72.0)
Requires-Dist: publication (>=0.0.3)
Requires-Dist: typeguard (~=2.13.3)
